{
  "entityType" : "DEVICE",
  "entity" : {
    "additionalInfo" : {
      "gateway" : false,
      "overwriteActivityTime" : false,
      "description" : ""
    },
    "customerId" : {
      "entityType" : "CUSTOMER",
      "id" : "db68cbf0-b16b-11ef-aaf6-af873acb8c03"
    },
    "deviceData" : {
      "configuration" : {
        "type" : "DEFAULT"
      },
      "transportConfiguration" : {
        "type" : "DEFAULT"
      }
    },
    "deviceProfileId" : {
      "entityType" : "DEVICE_PROFILE",
      "id" : "2b492950-b15b-11ef-ad3f-815eda72b584"
    },
    "externalId" : null,
    "firmwareId" : null,
    "id" : {
      "entityType" : "DEVICE",
      "id" : "2f79fd90-b162-11ef-aaf6-af873acb8c03"
    },
    "label" : "",
    "name" : "Toilet1.1",
    "softwareId" : null,
    "type" : "default"
  },
  "credentials" : {
    "credentialsId" : "i60Zg6uPxUvxFeiaPOy3",
    "credentialsType" : "ACCESS_TOKEN",
    "credentialsValue" : null
  },
  "relations" : [ {
    "additionalInfo" : null,
    "from" : {
      "entityType" : "ASSET",
      "id" : "4c7477a0-b161-11ef-aaf6-af873acb8c03"
    },
    "to" : {
      "entityType" : "DEVICE",
      "id" : "2f79fd90-b162-11ef-aaf6-af873acb8c03"
    },
    "type" : "Contains",
    "typeGroup" : "COMMON",
    "version" : 50
  } ],
  "attributes" : {
    "SERVER_SCOPE" : [ {
      "booleanValue" : false,
      "doubleValue" : null,
      "jsonValue" : null,
      "key" : "active",
      "lastUpdateTs" : 1738932178937,
      "longValue" : null,
      "strValue" : null
    }, {
      "booleanValue" : null,
      "doubleValue" : null,
      "jsonValue" : null,
      "key" : "inactivityAlarmTime",
      "lastUpdateTs" : 1738932178933,
      "longValue" : 1738932178933,
      "strValue" : null
    }, {
      "booleanValue" : null,
      "doubleValue" : null,
      "jsonValue" : null,
      "key" : "lastActivityTime",
      "lastUpdateTs" : 1738931526766,
      "longValue" : 1738931523980,
      "strValue" : null
    }, {
      "booleanValue" : null,
      "doubleValue" : null,
      "jsonValue" : null,
      "key" : "lastConnectTime",
      "lastUpdateTs" : 1733222108409,
      "longValue" : 1733222108409,
      "strValue" : null
    }, {
      "booleanValue" : null,
      "doubleValue" : null,
      "jsonValue" : null,
      "key" : "lastDisconnectTime",
      "lastUpdateTs" : 1733222108413,
      "longValue" : 1733222108413,
      "strValue" : null
    } ],
    "SHARED_SCOPE" : [ ]
  }
}